flaskslack/__init__.py
flaskslack/attachment.py
flaskslack/flaskslack.py
flaskslack/slack.py
flask_slack_template-0.0.7.dist-info/LICENSE
flask_slack_template-0.0.7.dist-info/METADATA
flask_slack_template-0.0.7.dist-info/WHEEL
flask_slack_template-0.0.7.dist-info/top_level.txt
flask_slack_template-0.0.7.dist-info/RECORD
