Metadata-Version: 2.1
Name: flask-slack-template
Version: 0.0.7
Summary: A light decorator around flask and slack to remove the boilerplate for handling Slack slash commands
Home-page: https://github.com/Jamiewu2/flask-slack-template
Author: Jamie Wu
Author-email: jamiewu2@illinois.com
License: UNKNOWN
Platform: UNKNOWN
Classifier: Programming Language :: Python :: 3
Classifier: License :: OSI Approved :: MIT License
Classifier: Operating System :: OS Independent
Classifier: Intended Audience :: Developers
Classifier: Topic :: Software Development :: Libraries :: Python Modules
Requires-Dist: Flask
Requires-Dist: slackclient (<2,>=1)
